README.rst
marktime.py
setup.py
marktime.egg-info/PKG-INFO
marktime.egg-info/SOURCES.txt
marktime.egg-info/dependency_links.txt
marktime.egg-info/top_level.txt