Metadata-Version: 1.1
Name: marktime
Version: 0.2.0
Summary: Python timer module for humans.
Home-page: https://github.com/ekalinin/marktime.py
Author: Eugene Kalinin
Author-email: e.v.kalinin@gmail.com
License: MIT
Keywords: timer,stopwatch,time
Platform: any
Classifier: Intended Audience :: Developers
Classifier: License :: OSI Approved :: MIT License
Classifier: Programming Language :: Python :: 2.7
Classifier: Programming Language :: Python :: 3.3
Classifier: Topic :: Software Development :: Libraries :: Python Modules
